symflow/__init__.py
symflow/symlayer.py
SymFlow-0.1.0.dist-info/METADATA
SymFlow-0.1.0.dist-info/WHEEL
SymFlow-0.1.0.dist-info/top_level.txt
SymFlow-0.1.0.dist-info/RECORD
