Metadata-Version: 2.1
Name: SymFlow
Version: 0.1.0
Summary: Library for using SymPy expressions as Keras layers.
Home-page: https://SymFlow.readthedocs.io/
Author: Paul Spiering
Author-email: paul@spiering.org
License: MIT
Platform: UNKNOWN
Classifier: Intended Audience :: Developers
Classifier: Intended Audience :: Science/Research
Classifier: License :: OSI Approved :: GNU General Public License v3 (GPLv3)
Classifier: Programming Language :: Python
Classifier: Programming Language :: Python :: 3
Classifier: Programming Language :: Python :: 3.6
Classifier: Programming Language :: Python :: 3.7
Classifier: Programming Language :: Python :: 3.8
Classifier: Programming Language :: Python :: 3.9
Classifier: Operating System :: OS Independent
Requires-Dist: numpy
Requires-Dist: tensorflow
Requires-Dist: sympy
